quicksift/__init__.py
quicksift/profiler.py
quicksift-0.1.4.dist-info/LICENSE
quicksift-0.1.4.dist-info/METADATA
quicksift-0.1.4.dist-info/WHEEL
quicksift-0.1.4.dist-info/RECORD
