Metadata-Version: 2.1
Name: quicksift
Version: 0.1.4
Summary: 
License: MIT
Author: chrisaddy
Author-email: chris.william.addy@gmail.com
Requires-Python: >=3.9,<4.0
Classifier: License :: OSI Approved :: MIT License
Classifier: Programming Language :: Python :: 3
Classifier: Programming Language :: Python :: 3.9
Classifier: Programming Language :: Python :: 3.10
Classifier: Programming Language :: Python :: 3.11
Requires-Dist: pandas (>=2.1.0,<3.0.0)
Requires-Dist: polars (>=0.19.3,<0.20.0)
